sage_bbb/__init__.py
sage_bbb/helpers/__init__.py
sage_bbb/helpers/meeting.py
sage_bbb/services/__init__.py
sage_bbb/services/client.py
sage_bbb/services/configurations.py
sage_bbb/services/factory.py
sage_bbb/services/meetings.py
sage_bbb/services/recordings.py
sage_bbb/utils.py
python_sage_bbb-0.1.3.dist-info/LICENSE
python_sage_bbb-0.1.3.dist-info/METADATA
python_sage_bbb-0.1.3.dist-info/WHEEL
python_sage_bbb-0.1.3.dist-info/RECORD
