Metadata-Version: 2.1
Name: python-sage-bbb
Version: 0.1.3
Summary: A Python client library for interacting with BigBlueButton API, enabling the creation and management of online meetings, recordings, and configurations.
License: MIT
Keywords: python,meet,BigBlueButton
Author: MohmdFo
Author-email: mohammad.fotouhi80@gmail.com
Requires-Python: >=3.10,<4.0
Classifier: Intended Audience :: Developers
Classifier: License :: OSI Approved :: MIT License
Classifier: Operating System :: OS Independent
Classifier: Programming Language :: Python :: 3
Classifier: Programming Language :: Python :: 3.10
Classifier: Programming Language :: Python :: 3.11
Classifier: Programming Language :: Python :: 3.12
Requires-Dist: requests (>=2.32.3,<3.0.0)
